{
"Bourgogne":"00362.geojson",
"Bourgogne Côte Chalonnaise":"00365.geojson",
"Bourgogne aligoté":"00389.geojson",
"Bourgogne mousseux":"00391.geojson",
"Bourgogne Passe-tout-grains":"00394.geojson",
"Crémant de Bourgogne":"00561.geojson",
"Montagny":"00863.geojson",
"Montagny premier cru Cornevent":"00866.geojson",
"Montagny premier cru La Condemine du Vieux Château":"00869.geojson",
"Montagny premier cru La Grande Pièce":"00870.geojson",
"Montagny premier cru Le Clos Chaudron":"00872.geojson",
"Montagny premier cru Le Clouzot":"00873.geojson",
"Montagny premier cru Le Vieux Château":"00874.geojson",
"Montagny premier cru Les Bassets":"00875.geojson",
"Montagny premier cru Les Bonneveaux":"00877.geojson",
"Montagny premier cru Les Coudrettes":"00885.geojson",
"Montagny premier cru Les Pidances":"00896.geojson",
"Montagny premier cru Les Vignes longues":"00901.geojson",
"Montagny premier cru Les Vignes des Prés":"00902.geojson",
"Montagny premier cru Mont Laurent":"00905.geojson",
"Montagny premier cru":"00913.geojson",
"Coteaux Bourguignons ou Bourgogne grand ordinaire ou Bourgogne ordinaire":"02338.geojson"
}
